{
    "results": [
        {
            "total": 0.896
        },
        {
            "total": 0.7925
        },
        {
            "total": 0.7116666666666667
        },
        {
            "total": 0.6395
        },
        {
            "total": 0.5968
        },
        {
            "total": 0.5886666666666667
        },
        {
            "total": 0.5444285714285715
        },
        {
            "total": 0.526625
        },
        {
            "total": 0.5106666666666667
        },
        {
            "total": 0.4662
        }
    ],
    "config": {}
}
